mchat_core/__init__.py
mchat_core/agent_manager.py
mchat_core/azure_auth.py
mchat_core/config.py
mchat_core/logging_utils.py
mchat_core/model_manager.py
mchat_core/terminator.py
mchat_core/tool_utils.py
mchat_core/tools/_fred.py
mchat_core/tools/_generate_image.py
mchat_core/tools/_rag.py
mchat_core/tools/_up_to_date.py
mchat_core/tools/_web_search.py
mchat_core-0.3.1.dist-info/licenses/LICENSE
mchat_core-0.3.1.dist-info/METADATA
mchat_core-0.3.1.dist-info/WHEEL
mchat_core-0.3.1.dist-info/top_level.txt
mchat_core-0.3.1.dist-info/RECORD
