Metadata-Version: 2.4
Name: mchat-core
Version: 0.3.1
Summary: Framework for building multi-agent chat applications with autogen
Author-email: jspv <jspvgithub@twinleaf.xyz>
License: MIT
Project-URL: Homepage, https://github.com/jspv/mchat_core
Project-URL: Repository, https://github.com/jspv/mchat_core
Project-URL: Issues, https://github.com/jspv/mchat_core/issues
Keywords: llm,agents,autogen,chat,tools
Classifier: Development Status :: 3 - Alpha
Classifier: Intended Audience :: Developers
Classifier: Topic :: Software Development :: Libraries
Classifier: Programming Language :: Python :: 3
Classifier: Programming Language :: Python :: 3.11
Classifier: Programming Language :: Python :: 3.12
Classifier: Programming Language :: Python :: 3.13
Classifier: Operating System :: OS Independent
Requires-Python: >=3.11
License-File: LICENSE
Requires-Dist: autogen-core>=0.7.5
Requires-Dist: autogen-agentchat>=0.7.5
Requires-Dist: autogen-ext[azure,mcp,openai]>=0.7.5
Requires-Dist: dynaconf>=3.2.11
Requires-Dist: playwright>=1.52.0
Requires-Dist: pyyaml>=6.0.2
Requires-Dist: rich>=14.0.0
Requires-Dist: tiktoken>=0.11.0
Requires-Dist: aiohttp>=3.12.15
Provides-Extra: dev
Requires-Dist: pytest>=8.4.0; extra == "dev"
Requires-Dist: pytest-asyncio>=1.0.0; extra == "dev"
Requires-Dist: pytest-forked>=1.6.0; extra == "dev"
Requires-Dist: mypy>=1.11.2; extra == "dev"
Requires-Dist: ruff>=0.8.4; extra == "dev"
Requires-Dist: toml>=0.10.2; extra == "dev"
Requires-Dist: ipykernel>=6.30.1; extra == "dev"
Provides-Extra: tools
Requires-Dist: bs4>=0.0.2; extra == "tools"
Requires-Dist: chromadb>=1.0.12; extra == "tools"
Requires-Dist: fredapi>=0.5.2; extra == "tools"
Requires-Dist: pypdf>=5.6.0; extra == "tools"
Requires-Dist: tzlocal>=5.3.1; extra == "tools"
Dynamic: license-file
